{
  "name": "AccountDropdown",
  "props": [
    {
      "name": "onSelect",
      "type": "function",
      "default": "required",
      "description": "A callback"
    },
    {
      "name": "urlState",
      "type": "object",
      "default": "",
      "description": ""
    },
    {
      "name": "className",
      "type": "string",
      "default": "",
      "description": ""
    },
    {
      "name": "style",
      "type": "object",
      "default": "",
      "description": ""
    },
    {
      "name": "title",
      "type": "string",
      "default": "\"Select account...\"",
      "description": ""
    },
    {
      "name": "withReportingEventTypes",
      "type": "object",
      "default": "",
      "description": ""
    }
  ]
}